graphite_api/__init__.py
graphite_api/app.py
graphite_api/carbonlink.py
graphite_api/config.py
graphite_api/encoders.py
graphite_api/functions.py
graphite_api/intervals.py
graphite_api/middleware.py
graphite_api/node.py
graphite_api/readers.py
graphite_api/search.py
graphite_api/storage.py
graphite_api/utils.py
graphite_api/_vendor/__init__.py
graphite_api/_vendor/whisper.py
graphite_api/finders/__init__.py
graphite_api/finders/whisper.py
graphite_api/render/__init__.py
graphite_api/render/attime.py
graphite_api/render/datalib.py
graphite_api/render/glyph.py
graphite_api/render/grammar.py
graphite_api-1.1.3.dist-info/DESCRIPTION.rst
graphite_api-1.1.3.dist-info/METADATA
graphite_api-1.1.3.dist-info/RECORD
graphite_api-1.1.3.dist-info/WHEEL
graphite_api-1.1.3.dist-info/metadata.json
graphite_api-1.1.3.dist-info/pbr.json
graphite_api-1.1.3.dist-info/top_level.txt
