Metadata-Version: 2.0
Name: graphite-api
Version: 1.1.3
Summary: Graphite-web, without the interface. Just the rendering HTTP API.
Home-page: https://github.com/brutasse/graphite-api
Author: Bruno Renié, based on Chris Davis's graphite-web
Author-email: bruno@renie.fr
License: Apache Software License 2.0
Platform: any
Classifier: Development Status :: 4 - Beta
Classifier: Environment :: Web Environment
Classifier: Framework :: Flask
Classifier: Intended Audience :: Developers
Classifier: Intended Audience :: System Administrators
Classifier: License :: OSI Approved :: Apache Software License
Classifier: Operating System :: OS Independent
Classifier: Programming Language :: Python
Classifier: Programming Language :: Python :: 2
Classifier: Programming Language :: Python :: 2.6
Classifier: Programming Language :: Python :: 2.7
Classifier: Programming Language :: Python :: 3
Classifier: Programming Language :: Python :: 3.2
Classifier: Programming Language :: Python :: 3.3
Classifier: Programming Language :: Python :: 3.4
Classifier: Topic :: Scientific/Engineering :: Information Analysis
Classifier: Topic :: Scientific/Engineering :: Visualization
Classifier: Topic :: System :: Monitoring
Requires-Dist: Flask
Requires-Dist: PyYAML
Requires-Dist: cairocffi
Requires-Dist: pyparsing (>=1.5.7)
Requires-Dist: pytz
Requires-Dist: six
Requires-Dist: structlog
Requires-Dist: tzlocal
Provides-Extra: cache
Requires-Dist: Flask-Cache; extra == 'cache'
Provides-Extra: cyanite
Requires-Dist: cyanite; extra == 'cyanite'
Provides-Extra: sentry
Requires-Dist: raven[flask]; extra == 'sentry'
Provides-Extra: statsd
Requires-Dist: statsd; extra == 'statsd'
